{
    "12": {
        "Item": 12,
        "Description": "SONF-T MOUTH FRESHNER TULSI",
        "Price": 2.5,
        "Quantity": 1,
        "POS": "SOFT TOFU",
        "Barcode": "028346078149",
        "PosSKU": "48973",
        "Size": "16 OZ",
        "SellingPrice": "2.49",
        "Department": "FROZENFOOD",
        "SellerCost": "2.49"
    },
    "LIC-P": {
        "Item": "LIC-P",
        "Description": "LAZIZA PAPPLE JELLY 85GMSX12",
        "Price": 8,
        "Quantity": 12,
        "POS": "JELL O",
        "Barcode": "043000200100",
        "PosSKU": "9428",
        "Size": "3 OZ 85 G",
        "SellingPrice": "0.79",
        "Department": "GROCERY",
        "SellerCost": "0.0"
    },
    "UC-B": {
        "Item": "UC-B",
        "Description": "LAZIZA BANANA JELLY 85GMSX12",
        "Price": 8,
        "Quantity": 12,
        "POS": "JELL O",
        "Barcode": "043000200100",
        "PosSKU": "9428",
        "Size": "3 OZ 85 G",
        "SellingPrice": "0.79",
        "Department": "GROCERY",
        "SellerCost": "0.0"
    },
    "LPAKORA": {
        "Item": "LPAKORA",
        "Description": "MIX LAZIZA PAKORA MIX 200GMS X 12",
        "Price": 18,
        "Quantity": 12,
        "POS": "LAZIZA PAKORA MIX",
        "Barcode": "5028217000984",
        "PosSKU": "11386",
        "Size": "200 GM ..",
        "SellingPrice": "1.99",
        "Department": "SPICES",
        "SellerCost": "1.5"
    },
    "CLAY": {
        "Item": "CLAY",
        "Description": "BOWLS CLAY BOWLS PER PC PLAIN",
        "Price": 2,
        "Quantity": 1,
        "POS": "ENO PLAIN",
        "Barcode": "8901571001064",
        "PosSKU": "6283",
        "Size": "100 GM",
        "SellingPrice": "2.99",
        "Department": "GROCERY",
        "SellerCost": "1.59"
    },
    "LKM-AS": {
        "Item": "LKM-AS",
        "Description": "LAZIZA KHEER MIX ALMSAF 155GM",
        "Price": 16,
        "Quantity": 1,
        "POS": "LAZIZA GAJAR KHEER MIX",
        "Barcode": "5028217001080",
        "PosSKU": "11348",
        "Size": "150 GM ..",
        "SellingPrice": "1.79",
        "Department": "GROCERY",
        "SellerCost": "1.33"
    },
    "TAWA": {
        "Item": "TAWA",
        "Description": "W KHAAS METAL TAWA W HANDLE",
        "Price": 6,
        "Quantity": 1,
        "POS": "KHAAS MIX",
        "Barcode": "184363000201",
        "PosSKU": "39524",
        "Size": "227 G",
        "SellingPrice": "1.99",
        "Department": "GROCERY",
        "SellerCost": "1.99"
    },
    "LKM-PC": {
        "Item": "LKM-PC",
        "Description": "LAZIZA KHEER MIX PISCOC 155GM",
        "Price": 16,
        "Quantity": 1,
        "POS": "LAZIZA MIXED PICKLE",
        "Barcode": "5028217002926",
        "PosSKU": "40989",
        "Size": "330 GM",
        "SellingPrice": "2.49",
        "Department": "PICKLE N PASTE",
        "SellerCost": "1.5"
    },
    "LDELHI": {
        "Item": "LDELHI",
        "Description": "PULAO LAZIZA DELHI PULAO 100GMS",
        "Price": 15,
        "Quantity": 1,
        "POS": "LAZIZA DELHI PULAO BIRYANI",
        "Barcode": "5028217002278",
        "PosSKU": "11330",
        "Size": "100 GM ..",
        "SellingPrice": "1.49",
        "Department": "GROCERY",
        "SellerCost": "1.25"
    },
    "RKSPS": {
        "Item": "RKSPS",
        "Description": "0-5 ROYAL KITCHEN SAUCE PAN 0-5",
        "Price": 45,
        "Quantity": 1,
        "POS": "ZP KITCHEN",
        "Barcode": "6933445182458",
        "PosSKU": "53335",
        "Size": "EA",
        "SellingPrice": "0.99",
        "Department": "MISCELLANEOUS",
        "SellerCost": "0.0"
    },
    "LCP-B-": {
        "Item": "LCP-B-",
        "Description": "LAZIZA BAN.. CUSTARD 300GMSX12",
        "Price": 15,
        "Quantity": 12,
        "POS": "BANANA CUSTARD",
        "Barcode": "8961014015935",
        "PosSKU": "64847",
        "Size": "285 GM ..",
        "SellingPrice": "2.29",
        "Department": "GROCERY",
        "SellerCost": "1.5"
    },
    "RK-TAWA": {
        "Item": "RK-TAWA",
        "Description": "11 ROYAL KITCHEN TAWA 11 INCHES",
        "Price": 7,
        "Quantity": 1,
        "POS": "ZP KITCHEN",
        "Barcode": "6933445182458",
        "PosSKU": "53335",
        "Size": "EA",
        "SellingPrice": "0.99",
        "Department": "MISCELLANEOUS",
        "SellerCost": "0.0"
    }
}